data_transformation_library/__init__.py
data_transformation_library/transformations.py
data_transformation_library-0.1.7.dist-info/METADATA
data_transformation_library-0.1.7.dist-info/WHEEL
data_transformation_library-0.1.7.dist-info/RECORD
