Metadata-Version: 2.1
Name: data-transformation-library
Version: 0.1.7
Summary: The Data Transformation Library is a Python library that provides a set of functions for common data transformation tasks. It is designed to simplify the process of handling and processing data, making it easier for developers to work with various types of data structures.
Author: alexstanc
Author-email: 50998432+alexstanc@users.noreply.github.com
Requires-Python: >=3.11,<4.0
Classifier: Programming Language :: Python :: 3
Classifier: Programming Language :: Python :: 3.11
Requires-Dist: numpy (>=1.25.2,<2.0.0)
Requires-Dist: pytest (>=7.4.1,<8.0.0)
